{
  "timestamp": "2026-01-13T22:52:51.577356",
  "total_trials_analyzed": 13700,
  "archived_trials": 3461,
  "current_ensemble_size": 20,
  "correlations": {
    "gamma": 0.3349,
    "min_cash_reserve": -0.3344,
    "norm_action": 0.2932,
    "norm_tech_exp": -0.2906,
    "volatility_penalty": -0.2855,
    "concentration_penalty": 0.2303,
    "kl_target": -0.205,
    "lookback": 0.199,
    "learning_rate": -0.1983,
    "eval_time_gap": -0.1888,
    "lr_schedule_factor": -0.1562,
    "thread_num": 0.1559,
    "batch_size": -0.1412,
    "gae_lambda": 0.14,
    "trailing_stop_pct": -0.1337,
    "norm_stocks_exp": -0.121,
    "value_loss_coef": -0.1051,
    "entropy_coef": -0.0956,
    "max_drawdown_penalty": 0.0945,
    "ppo_epochs": 0.0837,
    "max_grad_norm": -0.0732,
    "base_target_step": 0.0637,
    "clip_range": 0.0631,
    "base_break_step": 0.0617,
    "time_decay_floor": 0.0505,
    "net_dimension": 0.0436,
    "use_lr_schedule": 0.0335,
    "adam_epsilon": 0.0115,
    "worker_num": 0.0094,
    "norm_cash_exp": 0.0068,
    "norm_reward_exp": -0.0058,
    "lr_schedule_type": -0.0018
  },
  "parameter_sweet_spots": {
    "gamma": {
      "mean": 0.982115,
      "std": 0.011134,
      "min": 0.88,
      "max": 0.99
    },
    "min_cash_reserve": {
      "mean": 0.077941,
      "std": 0.041388,
      "min": 0.03,
      "max": 0.25
    },
    "norm_action": {
      "mean": 22938.164522,
      "std": 3078.791482,
      "min": 7000.0,
      "max": 25000.0
    },
    "norm_tech_exp": {
      "mean": -15.183548,
      "std": 0.560853,
      "min": -18.0,
      "max": -15.0
    },
    "volatility_penalty": {
      "mean": 0.006455,
      "std": 0.00903,
      "min": 0.0,
      "max": 0.05
    }
  },
  "interactions": [
    {
      "params": [
        "gamma",
        "min_cash_reserve"
      ],
      "correlation": -0.3258
    },
    {
      "params": [
        "gamma",
        "norm_action"
      ],
      "correlation": 0.3119
    },
    {
      "params": [
        "gamma",
        "norm_tech_exp"
      ],
      "correlation": -0.3655
    },
    {
      "params": [
        "min_cash_reserve",
        "norm_action"
      ],
      "correlation": -0.1134
    },
    {
      "params": [
        "min_cash_reserve",
        "norm_tech_exp"
      ],
      "correlation": 0.3019
    },
    {
      "params": [
        "norm_action",
        "norm_tech_exp"
      ],
      "correlation": -0.3457
    }
  ],
  "top_performers": {
    "count": 20,
    "mean_value": 0.143452,
    "trial_numbers": [
      191,
      192,
      26,
      83,
      25,
      157,
      156,
      87,
      86,
      195,
      172,
      179,
      177,
      173,
      194,
      178,
      166,
      180,
      144,
      190
    ]
  },
  "overlooked_trials": [
    {
      "trial_number": 191,
      "value": 0.156558,
      "rank_overall": 1
    },
    {
      "trial_number": 192,
      "value": 0.156517,
      "rank_overall": 2
    },
    {
      "trial_number": 26,
      "value": 0.156289,
      "rank_overall": 3
    },
    {
      "trial_number": 83,
      "value": 0.155774,
      "rank_overall": 4
    },
    {
      "trial_number": 25,
      "value": 0.155465,
      "rank_overall": 5
    },
    {
      "trial_number": 157,
      "value": 0.155207,
      "rank_overall": 6
    },
    {
      "trial_number": 87,
      "value": 0.154877,
      "rank_overall": 8
    },
    {
      "trial_number": 86,
      "value": 0.154592,
      "rank_overall": 9
    },
    {
      "trial_number": 195,
      "value": 0.133606,
      "rank_overall": 10
    },
    {
      "trial_number": 172,
      "value": 0.133569,
      "rank_overall": 11
    }
  ],
  "statistics": {
    "mean_value": 0.017665,
    "std_value": 0.029711,
    "best_value": 0.156558,
    "worst_value": -0.116391
  },
  "ai_insights": "### KEY FINDINGS\n\n1. **High Correlation with `gamma`:**\n   - The parameter `gamma` has a strong negative correlation with several other parameters such as `min_cash_reserve`, `norm_tech_exp`, and `volatility_penalty`. This suggests that high values of `gamma` might be detrimental to the performance of the model.\n\n2. **High-Performing Configurations:**\n   - The top-performing trials (trials 191, 192, 26, etc.) have a significantly higher mean value compared to the overall average and standard deviation. This indicates that there are configurations that perform exceptionally well but are often overlooked.\n\n3. **Parameter Sweet Spots:**\n   - Parameters like `gamma`, `min_cash_reserve`, and `norm_action` have specific ranges where their values yield better performance. For instance, `gamma` should be between 0.88 and 0.99 for optimal results.\n\n### OVERLOOKED OPPORTUNITIES\n\n1. **High-Performing Configurations:**\n   - The \"overlooked_trials\" data shows that trials with high values (e.g., trial number 191 with a value of 0.156558) should be reconsidered. These configurations might provide valuable insights into what works well and could potentially lead to better models.\n\n### PARAMETER RECOMMENDATIONS\n\n1. **`gamma`:**\n   - Focus on values between 0.88 and 0.99, as these are the sweet spots identified in the data.\n   \n2. **`min_cash_reserve`:**\n   - Aim for values between 0.03 and 0.25 to avoid excessive risk while maintaining a balance.\n\n3. **`norm_action`:**\n   - Target values around 22938.16, as this is the mean value of the sweet spot identified.\n   \n4. **`norm_tech_exp`:**\n   - Aim for values between -18.0 and -15.0 to leverage technical indicators effectively.\n\n### INTERACTIONS TO EXPLORE\n\n1. **`gamma` with `min_cash_reserve`:**\n   - Explore how the negative correlation between these parameters affects performance, as reducing `gamma` might alleviate the need for a higher cash reserve.\n   \n2. **`gamma` with `norm_action`:**\n   - Investigate if increasing `gamma` can compensate for lower action normalization values, potentially improving overall performance.\n\n3. **`min_cash_reserve` with `norm_tech_exp`:**\n   - Examine how these parameters interact to optimize trading strategies that balance risk and technical analysis.\n\n### ACTIONABLE SUGGESTIONS\n\n1. **Re-evaluate High-Performing Configurations:**\n   - Conduct a detailed review of the top-performing trials (trials 191, 192, etc.) to identify commonalities in their configurations. This could lead to new insights and potentially better parameter ranges.\n\n2. **Adjust Parameter Ranges Based on Sweet Spots:**\n   - Implement tighter constraints around identified sweet spots for parameters like `gamma`, `min_cash_reserve`, and `norm_action`. For example, set `gamma` between 0.88 and 0.99 and `min_cash_reserve` between 0.03 and 0.25.\n\n3. **Explore Parameter Interactions:**\n   - Introduce parameter sweeps that explore the interactions between `gamma`, `min_cash_reserve`, and `norm_tech_exp`. This could help in identifying more effective combinations that might not be obvious from individual parameter analysis.\n\nBy focusing on these actionable suggestions, future training runs can be optimized to better leverage the identified patterns and configurations."
}